git_ctx/__init__.py
git_ctx/cli.py
gitcontext-0.2.1.dist-info/METADATA
gitcontext-0.2.1.dist-info/WHEEL
gitcontext-0.2.1.dist-info/entry_points.txt
gitcontext-0.2.1.dist-info/top_level.txt
gitcontext-0.2.1.dist-info/RECORD
