Metadata-Version: 2.4
Name: gitcontext
Version: 0.2.1
Summary: Context-aware git CLI for multi-project research repos with worktree, squash, and fzf support.
Author-email: AxOr <axiomsandorbits@gmail.com>
License: MIT
Project-URL: Homepage, https://github.com/ax-or/gitcontext.git
Project-URL: Repository, https://github.com/ax-or/gitcontext.git
Project-URL: Issues, https://github.com/ax-or/gitcontext/issues
Requires-Python: >=3.8
Requires-Dist: click>=8.0
Provides-Extra: dev
Requires-Dist: pytest>=7.0; extra == "dev"
Requires-Dist: ruff>=0.1.0; extra == "dev"
Requires-Dist: black>=23.0; extra == "dev"
Requires-Dist: pre-commit>=3.0; extra == "dev"
